<annotation>
	<folder>XML</folder>
	<filename>01315.jpg</filename>
	<path>E:\datasets\fire\3\new\01315.jpg</path>
	<source>
		<database>Unknown</database>
	</source>
	<size>
		<width>899</width>
		<height>674</height>
		<depth>3</depth>
	</size>
	<segmented>0</segmented>
	<object>
		<name>0</name>
		<pose>Unspecified</pose>
		<truncated>0</truncated>
		<difficult>0</difficult>
		<bndbox>
			<xmin>296</xmin>
			<ymin>319</ymin>
			<xmax>511</xmax>
			<ymax>543</ymax>
		</bndbox>
	</object>
	<object>
		<name>0</name>
		<pose>Unspecified</pose>
		<truncated>0</truncated>
		<difficult>0</difficult>
		<bndbox>
			<xmin>669</xmin>
			<ymin>279</ymin>
			<xmax>891</xmax>
			<ymax>590</ymax>
		</bndbox>
	</object>
</annotation>
