<annotation>
	<folder>XML</folder>
	<filename>01438.jpg</filename>
	<path>E:\datasets\fire\3\new\01438.jpg</path>
	<source>
		<database>Unknown</database>
	</source>
	<size>
		<width>720</width>
		<height>502</height>
		<depth>3</depth>
	</size>
	<segmented>0</segmented>
	<object>
		<name>0</name>
		<pose>Unspecified</pose>
		<truncated>0</truncated>
		<difficult>0</difficult>
		<bndbox>
			<xmin>53</xmin>
			<ymin>118</ymin>
			<xmax>214</xmax>
			<ymax>418</ymax>
		</bndbox>
	</object>
	<object>
		<name>0</name>
		<pose>Unspecified</pose>
		<truncated>0</truncated>
		<difficult>0</difficult>
		<bndbox>
			<xmin>245</xmin>
			<ymin>196</ymin>
			<xmax>383</xmax>
			<ymax>371</ymax>
		</bndbox>
	</object>
</annotation>
